okxv5/Account_api.py
okxv5/Affiliate_api.py
okxv5/Broker_api.py
okxv5/Convert_api.py
okxv5/Copytrading_api.py
okxv5/FDBroker_api.py
okxv5/Finance_api.py
okxv5/Funding_api.py
okxv5/Market_api.py
okxv5/Public_api.py
okxv5/Recurring_api.py
okxv5/Rfq_api.py
okxv5/Singal_api.py
okxv5/SprdApi_api.py
okxv5/Trade_api.py
okxv5/TradingBot_api.py
okxv5/TradingData_api.py
okxv5/__init__.py
okxv5/client.py
okxv5/consts.py
okxv5/exceptions.py
okxv5/status_api.py
okxv5/subAccount_api.py
okxv5/utils.py
okxv5-1.8.13.dist-info/METADATA
okxv5-1.8.13.dist-info/WHEEL
okxv5-1.8.13.dist-info/top_level.txt
okxv5-1.8.13.dist-info/RECORD
