Metadata-Version: 2.1
Name: okxv5
Version: 1.8.13
Summary: okx RestAPI
Home-page: 
Author: 
Author-email: 
License: Apache-2.0
Keywords: okx,v5,RestAPI
Requires-Dist: requests
Requires-Dist: PyYAML
Requires-Dist: numpy
Requires-Dist: pandas
